link_monitor/__init__.py
link_monitor/cli.py
link_monitor/logger.py
link_monitor/monitor.py
link_monitor/ping.py
py_link_monitor-0.1.1.dist-info/LICENSE
py_link_monitor-0.1.1.dist-info/METADATA
py_link_monitor-0.1.1.dist-info/WHEEL
py_link_monitor-0.1.1.dist-info/entry_points.txt
py_link_monitor-0.1.1.dist-info/RECORD
