Metadata-Version: 2.1
Name: py-link-monitor
Version: 0.1.1
Summary: Link monitor written on Python that uses command line ping utility
License: MIT
Author: Mykhailo  Volkov
Author-email: mvolkov83@gmail.com
Requires-Python: >=3.9,<4.0
Classifier: License :: OSI Approved :: MIT License
Classifier: Programming Language :: Python :: 3
Classifier: Programming Language :: Python :: 3.9
Classifier: Programming Language :: Python :: 3.10
Classifier: Programming Language :: Python :: 3.11
Requires-Dist: pingparsing (==1.4.1)
